{"cameraMode":{"drawMode":0,"name":"Shaded","section":"Shading Mode"},"sceneLighting":true,"audioPlay":false,"sceneViewState":{"m_AlwaysRefresh":false,"showFog":true,"showSkybox":true,"showFlares":true,"showImageEffects":true,"showParticleSystems":true,"showVisualEffectGraphs":true,"m_FxEnabled":true},"in2DMode":false,"pivot":{"x":-82.94682312011719,"y":-111.40895080566406,"z":942.5321044921875},"rotation":{"x":0.37905505299568179,"y":0.01248643547296524,"z":-0.005117329768836498,"w":0.9252809882164002},"size":188.22401428222657,"orthographic":false}